withworld/__init__.py
withworld/api.py
withworld/array.py
withworld/autokey.py
withworld/browser.py
withworld/bufer.py
withworld/django.py
withworld/telegram.py
withworld-0.1.32.dist-info/licenses/LICENSE
withworld-0.1.32.dist-info/METADATA
withworld-0.1.32.dist-info/WHEEL
withworld-0.1.32.dist-info/top_level.txt
withworld-0.1.32.dist-info/RECORD
