Metadata-Version: 2.4
Name: withworld
Version: 0.1.32
Summary: Инструменты
Author-email: Игорь Фокин <withworld@yandex.ru>
License: MIT License
Requires-Python: >=3.8
License-File: LICENSE
Requires-Dist: pyautogui
Requires-Dist: pyperclip
Requires-Dist: pynput
Requires-Dist: requests
Requires-Dist: python-dotenv
Requires-Dist: psycopg2-binary
Requires-Dist: django
Requires-Dist: aiogram
Requires-Dist: asgiref
Requires-Dist: asyncpg
Requires-Dist: gunicorn
Requires-Dist: uvicorn
Requires-Dist: channels
Requires-Dist: websockets
Requires-Dist: httptools
Requires-Dist: channels_redis
Dynamic: license-file
